Metadata-Version: 2.1
Name: elasticwrapper
Version: 0.0.1
Summary: Automatically chooses between versioned Elasticsearch imports
Home-page: https://github.com/bra-fsn/elasticwrapper
Author: NAGY, Attila
Author-email: nagy.attila@gmail.com
License: UNKNOWN
Platform: UNKNOWN
Classifier: Programming Language :: Python
Classifier: License :: OSI Approved :: MIT License
Classifier: Operating System :: OS Independent
